mistral_ansible_actions.py
mistral_ansible_actions-0.1.2.dev1.dist-info/DESCRIPTION.rst
mistral_ansible_actions-0.1.2.dev1.dist-info/METADATA
mistral_ansible_actions-0.1.2.dev1.dist-info/RECORD
mistral_ansible_actions-0.1.2.dev1.dist-info/WHEEL
mistral_ansible_actions-0.1.2.dev1.dist-info/entry_points.txt
mistral_ansible_actions-0.1.2.dev1.dist-info/metadata.json
mistral_ansible_actions-0.1.2.dev1.dist-info/pbr.json
mistral_ansible_actions-0.1.2.dev1.dist-info/top_level.txt
