Metadata-Version: 2.0
Name: mistral-ansible-actions
Version: 0.1.2.dev1
Summary: A Mistral action to execute Ansible playbooks
Home-page: https://github.com/d0ugal/mistral-ansible-actions
Author: Dougal Matthews
Author-email: dougal@redhat.com
License: Apache-2
Platform: UNKNOWN
Classifier: Intended Audience :: Developers
Classifier: Natural Language :: English
Classifier: License :: OSI Approved :: Apache Software License
Classifier: Programming Language :: Python
Classifier: Programming Language :: Python :: 2.7
Classifier: Programming Language :: Python :: 3.3
Classifier: Programming Language :: Python :: 3.4
Classifier: Programming Language :: Python :: 3.5
Classifier: Topic :: Internet
Classifier: Topic :: Utilities
